<?xml version="1.0"?>
<scene>
  <BOX uuid="f9b926d2-a974-4060-ac46-b50eacc22681" name="" selectable="True" position="19.015451431,60.433300018,6.070271969" size="0.500000000,4.000000000,4.000000000" orientation="-0.073139980,-0.355937839,0.876878321,0.314711243" local_position="0.000000000,0.000000000,0.000000000" local_size="1.000000000,1.000000000,1.000000000" local_orientation="1.000000000,0.000000000,0.000000000,0.000000000" scaling="Fixed" final_shape="False" cast_shadows="False" colour="0.000000000,0.000000000,1.000000000" alpha="0.20000000298"/>
  <BOX uuid="9ffe9a15-914a-4597-a75f-ecd1eced8297" name="" selectable="True" position="12.679142952,54.683055878,5.265131474" size="0.500000000,4.000000000,4.000000000" orientation="0.110205263,-0.697937131,0.706513405,0.039715808" local_position="0.000000000,0.000000000,0.000000000" local_size="1.000000000,1.000000000,1.000000000" local_orientation="1.000000000,0.000000000,0.000000000,0.000000000" scaling="Fixed" final_shape="False" cast_shadows="False" colour="0.000000000,0.000000000,1.000000000" alpha="0.20000000298"/>
  <BOX uuid="1a281b83-85d5-4ca5-9e5b-e67159c10194" name="" selectable="True" position="12.955038071,31.064212799,5.862138748" size="0.500000000,4.000000000,4.000000000" orientation="-0.405787289,-0.575313926,0.566305399,-0.428542554" local_position="0.000000000,0.000000000,0.000000000" local_size="1.000000000,1.000000000,1.000000000" local_orientation="1.000000000,0.000000000,0.000000000,0.000000000" scaling="Fixed" final_shape="False" cast_shadows="False" colour="0.000000000,0.000000000,1.000000000" alpha="0.20000000298"/>
  <BOX uuid="f8944bca-3a9b-4c6d-93c2-5c553a1e4f96" name="" selectable="True" position="13.562136650,3.768501282,7.052249432" size="0.500000000,4.000000000,4.000000000" orientation="0.423715711,-0.461572051,0.598154545,0.499627203" local_position="0.000000000,0.000000000,0.000000000" local_size="1.000000000,1.000000000,1.000000000" local_orientation="1.000000000,0.000000000,0.000000000,0.000000000" scaling="Fixed" final_shape="False" cast_shadows="False" colour="0.000000000,0.000000000,1.000000000" alpha="0.20000000298"/>
  <BOX uuid="2563ca30-304a-4192-99f7-ba75a77a6e36" name="" selectable="True" position="19.015451431,60.433300018,6.070271969" size="0.500000000,4.000000000,4.000000000" orientation="0.329329193,-0.852780104,0.387138039,-0.120135687" local_position="0.000000000,0.000000000,0.000000000" local_size="1.000000000,1.000000000,1.000000000" local_orientation="1.000000000,0.000000000,0.000000000,0.000000000" scaling="Fixed" final_shape="False" cast_shadows="False" colour="0.000000000,0.000000000,1.000000000" alpha="0.20000000298"/>
  <BOX uuid="ba59f0e6-fa6f-4c5a-b1ae-9cf023d6623c" name="" selectable="True" position="24.732774734,54.143062592,5.641036510" size="0.500000000,4.000000000,4.000000000" orientation="0.060974374,-0.674450934,0.729597807,0.095315710" local_position="0.000000000,0.000000000,0.000000000" local_size="1.000000000,1.000000000,1.000000000" local_orientation="1.000000000,0.000000000,0.000000000,0.000000000" scaling="Fixed" final_shape="False" cast_shadows="False" colour="0.000000000,0.000000000,1.000000000" alpha="0.20000000298"/>
  <BOX uuid="05065de6-534a-4ddc-9f30-fd97b05a9094" name="" selectable="True" position="26.049264908,30.630897522,6.138429165" size="0.500000000,4.000000000,4.000000000" orientation="-0.425668955,-0.578260779,0.565700412,-0.405466914" local_position="0.000000000,0.000000000,0.000000000" local_size="1.000000000,1.000000000,1.000000000" local_orientation="1.000000000,0.000000000,0.000000000,0.000000000" scaling="Fixed" final_shape="False" cast_shadows="False" colour="0.000000000,0.000000000,1.000000000" alpha="0.20000000298"/>
  <BOX uuid="35504bd3-ef05-4c80-bee7-595223ae7b97" name="" selectable="True" position="26.132759094,3.331560135,7.073090553" size="0.500000000,4.000000000,4.000000000" orientation="0.516343176,-0.621608675,0.427541584,0.405216753" local_position="0.000000000,0.000000000,0.000000000" local_size="1.000000000,1.000000000,1.000000000" local_orientation="1.000000000,0.000000000,0.000000000,0.000000000" scaling="Fixed" final_shape="False" cast_shadows="False" colour="0.000000000,0.000000000,1.000000000" alpha="0.20000000298"/>
  <BOX uuid="adfd950e-6be2-48e4-ac06-5d179ab46a1f" name="" selectable="True" position="19.015451431,60.433300018,6.070271969" size="0.500000000,4.000000000,4.000000000" orientation="0.720574319,-0.091523670,0.072793752,0.683445036" local_position="0.000000000,0.000000000,0.000000000" local_size="1.000000000,1.000000000,1.000000000" local_orientation="1.000000000,0.000000000,0.000000000,0.000000000" scaling="Fixed" final_shape="False" cast_shadows="False" colour="0.000000000,0.000000000,1.000000000" alpha="0.20000000298"/>
  <BOX uuid="645215a8-18c6-40c6-a562-a6086de8e24d" name="" selectable="True" position="19.561660767,70.564842224,4.588906765" size="0.500000000,4.000000000,4.000000000" orientation="0.720147967,0.046784364,-0.094853885,0.685711980" local_position="0.000000000,0.000000000,0.000000000" local_size="1.000000000,1.000000000,1.000000000" local_orientation="1.000000000,0.000000000,0.000000000,0.000000000" scaling="Fixed" final_shape="False" cast_shadows="False" colour="0.000000000,0.000000000,1.000000000" alpha="0.20000000298"/>
  <BOX uuid="5811b4fa-67eb-4b8e-9402-bf0d73d3ea12" name="" selectable="True" position="20.224788666,86.341499329,7.843649864" size="0.500000000,4.000000000,4.000000000" orientation="0.028801287,0.005180219,0.693470240,0.719890773" local_position="0.000000000,0.000000000,0.000000000" local_size="1.000000000,1.000000000,1.000000000" local_orientation="1.000000000,0.000000000,0.000000000,0.000000000" scaling="Fixed" final_shape="False" cast_shadows="False" colour="0.000000000,0.000000000,1.000000000" alpha="0.20000000298"/>
  <BOX uuid="596ae36b-fc8c-4d76-a9ca-03830ac93b87" name="" selectable="True" position="10.213720322,85.952262878,7.377439022" size="0.500000000,4.000000000,4.000000000" orientation="-0.171826690,-0.220811680,0.647303581,0.709024549" local_position="0.000000000,0.000000000,0.000000000" local_size="1.000000000,1.000000000,1.000000000" local_orientation="1.000000000,0.000000000,0.000000000,0.000000000" scaling="Fixed" final_shape="False" cast_shadows="False" colour="0.000000000,0.000000000,1.000000000" alpha="0.20000000298"/>
  <BOX uuid="eb26f240-db12-431e-9f36-2d82c9f1fdf0" name="" selectable="True" position="6.699910641,66.242759705,4.589453697" size="0.500000000,4.000000000,4.000000000" orientation="-0.082581021,-0.701572359,0.213908285,0.674699783" local_position="0.000000000,0.000000000,0.000000000" local_size="1.000000000,1.000000000,1.000000000" local_orientation="1.000000000,0.000000000,0.000000000,0.000000000" scaling="Fixed" final_shape="False" cast_shadows="False" colour="0.000000000,0.000000000,1.000000000" alpha="0.20000000298"/>
  <BOX uuid="efc1cc71-2cf9-4b08-ad6a-c97005f102fe" name="" selectable="True" position="4.747791767,52.852443695,0.773349285" size="0.500000000,4.000000000,4.000000000" orientation="-0.378356278,-0.526084840,0.553099275,0.523605227" local_position="0.000000000,0.000000000,0.000000000" local_size="1.000000000,1.000000000,1.000000000" local_orientation="1.000000000,0.000000000,0.000000000,0.000000000" scaling="Fixed" final_shape="False" cast_shadows="False" colour="0.000000000,0.000000000,1.000000000" alpha="0.20000000298"/>
  <BOX uuid="cc5eeb75-4860-438c-8f27-50b5a24f4c0e" name="" selectable="True" position="20.224788666,86.341499329,7.843649864" size="0.500000000,4.000000000,4.000000000" orientation="0.695660412,-0.717774510,0.006165688,-0.028606715" local_position="0.000000000,0.000000000,0.000000000" local_size="1.000000000,1.000000000,1.000000000" local_orientation="1.000000000,0.000000000,0.000000000,0.000000000" scaling="Fixed" final_shape="False" cast_shadows="False" colour="0.000000000,0.000000000,1.000000000" alpha="0.20000000298"/>
  <BOX uuid="c4aa8907-9897-4dc4-b28e-0c92d9769a04" name="" selectable="True" position="30.108768463,85.018737793,8.156435013" size="0.500000000,4.000000000,4.000000000" orientation="0.699545860,-0.638578653,0.221356779,-0.232064798" local_position="0.000000000,0.000000000,0.000000000" local_size="1.000000000,1.000000000,1.000000000" local_orientation="1.000000000,0.000000000,0.000000000,0.000000000" scaling="Fixed" final_shape="False" cast_shadows="False" colour="0.000000000,0.000000000,1.000000000" alpha="0.20000000298"/>
  <BOX uuid="acefd2f7-3808-4dd8-b64f-66d917ad5e1a" name="" selectable="True" position="32.901222229,65.223762512,6.855759621" size="0.500000000,4.000000000,4.000000000" orientation="0.718033254,-0.209829256,0.650724471,-0.130221412" local_position="0.000000000,0.000000000,0.000000000" local_size="1.000000000,1.000000000,1.000000000" local_orientation="1.000000000,0.000000000,0.000000000,0.000000000" scaling="Fixed" final_shape="False" cast_shadows="False" colour="0.000000000,0.000000000,1.000000000" alpha="0.20000000298"/>
  <BOX uuid="7733a41b-9afc-4213-9cea-28aa4774abb2" name="" selectable="True" position="34.953643799,53.399688721,-0.604427338" size="0.500000000,4.000000000,4.000000000" orientation="0.574730992,-0.493855774,0.589906633,-0.278928190" local_position="0.000000000,0.000000000,0.000000000" local_size="1.000000000,1.000000000,1.000000000" local_orientation="1.000000000,0.000000000,0.000000000,0.000000000" scaling="Fixed" final_shape="False" cast_shadows="False" colour="0.000000000,0.000000000,1.000000000" alpha="0.20000000298"/>
  <BOX uuid="3cf11e30-b9cf-4982-84ba-773ad5faf5e2" name="" selectable="True" position="20.224788666,86.341499329,7.843649864" size="0.500000000,4.000000000,4.000000000" orientation="0.723033726,-0.059858821,0.039349064,0.687088668" local_position="0.000000000,0.000000000,0.000000000" local_size="1.000000000,1.000000000,1.000000000" local_orientation="1.000000000,0.000000000,0.000000000,0.000000000" scaling="Fixed" final_shape="False" cast_shadows="False" colour="0.000000000,0.000000000,1.000000000" alpha="0.20000000298"/>
  <BOX uuid="83db37d6-4405-498b-8602-149bb901180a" name="" selectable="True" position="20.617008209,95.523033142,7.368653774" size="0.500000000,4.000000000,4.000000000" orientation="0.718838990,0.046323519,-0.071476154,0.689939022" local_position="0.000000000,0.000000000,0.000000000" local_size="1.000000000,1.000000000,1.000000000" local_orientation="1.000000000,0.000000000,0.000000000,0.000000000" scaling="Fixed" final_shape="False" cast_shadows="False" colour="0.000000000,0.000000000,1.000000000" alpha="0.20000000298"/>
  <BOX uuid="09bf667b-e600-48ed-999d-a3e8e4d564e6" name="" selectable="True" position="12.199104309,2.094538212,-2.716285467" size="1.000000000,4.000000000,4.000000000" orientation="0.139544502,-0.677140832,0.698998272,0.182781279" local_position="0.000000000,0.000000000,0.000000000" local_size="1.000000000,1.000000000,1.000000000" local_orientation="1.000000000,0.000000000,0.000000000,0.000000000" scaling="Fixed" final_shape="False" cast_shadows="False" colour="0.000000000,1.000000000,1.000000000" alpha="0.5"/>
  <BOX uuid="e0e824c6-18ba-4b03-b22f-1cff17cca9a0" name="" selectable="True" position="27.800895691,2.094522953,-2.716260910" size="1.000000000,4.000000000,4.000000000" orientation="0.182780966,-0.698998272,0.677140892,0.139544770" local_position="0.000000000,0.000000000,0.000000000" local_size="1.000000000,1.000000000,1.000000000" local_orientation="1.000000000,0.000000000,0.000000000,0.000000000" scaling="Fixed" final_shape="False" cast_shadows="False" colour="0.000000000,1.000000000,1.000000000" alpha="0.5"/>
  <DYNAMIC_ACTOR uuid="85137694-87ef-4bd3-a279-0e83e8f7694f" name="Bone" selectable="True" shapes="['faf7a3be-43d3-48ad-820c-8134cfad9372']" position="19.110792160,61.372421265,4.553245544" orientation="0.517624378,-0.498010695,0.506548464,0.476926655" mass="9.54638195038"/>
  <PHYSIC_SHAPE uuid="faf7a3be-43d3-48ad-820c-8134cfad9372" name="" selectable="True" position="19.110801697,61.372402191,4.554136276" size="5.027153015,7.443857193,3.188810110" orientation="0.517616928,-0.498020589,0.506556094,0.476916313" local_position="0.000000000,0.000000000,0.000000000" local_size="5.027153015,7.443857193,3.188810110" local_orientation="1.000000000,0.000000000,0.000000000,0.000000000" scaling="Fixed" final_shape="False" cast_shadows="True" shape="box" actor="85137694-87ef-4bd3-a279-0e83e8f7694f"/>
  <DYNAMIC_ACTOR uuid="e3be0d2e-cef5-4f63-b73e-d4447353f5e6" name="Bone.001" selectable="True" shapes="['7967e20b-09cc-4d4d-9941-cd60d8ec735d']" position="13.720220566,56.213813782,6.525403500" orientation="-0.071313195,-0.354792684,0.878259420,0.312565207" mass="1.05599999428"/>
  <PHYSIC_SHAPE uuid="7967e20b-09cc-4d4d-9941-cd60d8ec735d" name="" selectable="True" position="13.720123291,56.213790894,6.526004791" size="3.299999952,2.000000000,2.000000000" orientation="-0.071315832,-0.354791939,0.878258407,0.312568247" local_position="0.000000000,0.000000000,0.000000000" local_size="3.299999952,2.000000000,2.000000000" local_orientation="1.000000000,0.000000000,0.000000000,0.000000000" scaling="1To1" final_shape="False" cast_shadows="True" shape="box" actor="e3be0d2e-cef5-4f63-b73e-d4447353f5e6"/>
  <JOINT uuid="8ebef3b4-24ec-4ff6-840e-5d2e62dc5342" name="" selectable="True" shapes="['f9b926d2-a974-4060-ac46-b50eacc22681']" body1="85137694-87ef-4bd3-a279-0e83e8f7694f" body2="e3be0d2e-cef5-4f63-b73e-d4447353f5e6" anchor1="-1.508145690,0.000000000,-0.956643164" anchor2="-6.599999905,-1.000000000,0.600000024" anchor1orientation="0.733684838,0.038114008,0.503956437,0.454182476" anchor2orientation="1.000000000,0.000000000,0.000000000,0.000000000" ylimit="9.99998874818e-08" zlimit="9.99998874818e-08" motor_target="1.000000000,0.000000000,0.000000000,0.000000000" motor_on="True"/>
  <DYNAMIC_ACTOR uuid="dead4a4b-ae6b-4259-93fb-2738cc224787" name="Bone.009" selectable="True" shapes="['5133c4f0-fa8e-4d6c-8e0c-c8af273c73ab']" position="12.817156792,42.873653412,5.563115120" orientation="0.027162835,-0.710703075,0.701551616,-0.044594023" mass="8.1037979126"/>
  <PHYSIC_SHAPE uuid="5133c4f0-fa8e-4d6c-8e0c-c8af273c73ab" name="" selectable="True" position="12.817090034,42.873634338,5.563634396" size="11.814002037,2.928200245,2.928200245" orientation="0.027162870,-0.710704207,0.701550782,-0.044588983" local_position="0.000000000,0.000000000,0.000000000" local_size="11.814002037,2.928200245,2.928200245" local_orientation="1.000000000,0.000000000,0.000000000,0.000000000" scaling="1To1" final_shape="False" cast_shadows="True" shape="box" actor="dead4a4b-ae6b-4259-93fb-2738cc224787"/>
  <JOINT uuid="3d174f5b-72fb-402a-b319-066b19e025d6" name="" selectable="True" shapes="['9ffe9a15-914a-4597-a75f-ecd1eced8297']" body1="e3be0d2e-cef5-4f63-b73e-d4447353f5e6" body2="dead4a4b-ae6b-4259-93fb-2738cc224787" anchor1="1.912220478,-0.999999046,0.600000978" anchor2="-11.814000130,-0.000000274,-0.000000146" anchor1orientation="0.872678339,0.274826825,0.056887846,-0.399582922" anchor2orientation="1.000000000,0.000000000,0.000000000,0.000000000" ylimit="69.9999313354" zlimit="69.9999313354" motor_target="0.984807789,0.000000000,0.173648208,0.000000000" motor_on="True"/>
  <DYNAMIC_ACTOR uuid="1c1432fd-9a0e-42d0-a154-cc4dc900ccc0" name="Bone.011" selectable="True" shapes="['aca14f41-0866-4e55-865f-d75e7bc53780']" position="13.246552467,17.409683228,6.458447456" orientation="-0.006722218,-0.715197265,0.698484302,-0.023821127" mass="4.37046957016"/>
  <PHYSIC_SHAPE uuid="aca14f41-0866-4e55-865f-d75e7bc53780" name="" selectable="True" position="13.246541977,17.409658432,6.458702564" size="13.657718658,2.000000000,2.000000000" orientation="-0.006721714,-0.715198278,0.698483348,-0.023817610" local_position="0.000000000,0.000000000,0.000000000" local_size="13.657718658,2.000000000,2.000000000" local_orientation="1.000000000,0.000000000,0.000000000,0.000000000" scaling="1To1" final_shape="False" cast_shadows="True" shape="box" actor="1c1432fd-9a0e-42d0-a154-cc4dc900ccc0"/>
  <JOINT uuid="fb5bb77d-018e-4aa2-a444-d6b741e35ee0" name="" selectable="True" shapes="['1a281b83-85d5-4ca5-9e5b-e67159c10194']" body1="dead4a4b-ae6b-4259-93fb-2738cc224787" body2="1c1432fd-9a0e-42d0-a154-cc4dc900ccc0" anchor1="11.814000130,0.000000013,-0.000001338" anchor2="-13.657726288,-0.000000514,-0.000001097" anchor1orientation="0.814256132,-0.028628536,0.578977346,-0.030870406" anchor2orientation="1.000000000,0.000000000,0.000000000,0.000000000" ylimit="79.9999008179" zlimit="9.9999961853" motor_target="0.819152176,0.000000000,-0.573576570,0.000000000" motor_on="True"/>
  <DYNAMIC_ACTOR uuid="f99f27d0-68d9-479f-957d-8b88ddfe7656" name="Bone.013" selectable="True" shapes="['f0ecaeef-33df-48d5-a9ce-214de540231f']" position="12.999556541,3.098680496,3.226149082" orientation="0.434654027,-0.495222121,0.583460510,0.474768162" mass="1.56815993786"/>
  <PHYSIC_SHAPE uuid="f0ecaeef-33df-48d5-a9ce-214de540231f" name="" selectable="True" position="12.999548912,3.098680496,3.226150036" size="4.900499821,2.000000000,2.000000000" orientation="0.434654176,-0.495222598,0.583460033,0.474768072" local_position="0.000000000,0.000000000,0.000000000" local_size="4.900499821,2.000000000,2.000000000" local_orientation="1.000000000,0.000000000,0.000000000,0.000000000" scaling="1To1" final_shape="False" cast_shadows="True" shape="box" actor="f99f27d0-68d9-479f-957d-8b88ddfe7656"/>
  <JOINT uuid="8926df68-b341-4c1c-9edc-a84d8c9fb706" name="" selectable="True" shapes="['f8944bca-3a9b-4c6d-93c2-5c553a1e4f96']" body1="1c1432fd-9a0e-42d0-a154-cc4dc900ccc0" body2="f99f27d0-68d9-479f-957d-8b88ddfe7656" anchor1="13.657711029,0.000000014,-0.000001465" anchor2="-3.920400381,0.000000050,0.000003108" anchor1orientation="0.733168483,-0.057084575,-0.668305039,0.112132229" anchor2orientation="1.000000000,0.000000000,0.000000000,0.000000000" ylimit="79.9999008179" zlimit="29.9999961853" motor_target="1.000000000,0.000000000,0.000000000,0.000000000" motor_on="True"/>
  <DYNAMIC_ACTOR uuid="6c39c50b-11e7-4c91-8f51-64d65ff9caaa" name="Bone.004" selectable="True" shapes="['4cb91715-7c1b-4fee-a341-417a1451a94d']" position="24.305456161,56.321369171,5.942344666" orientation="0.329326391,-0.852877736,0.386913270,-0.120174155" mass="1.05599999428"/>
  <PHYSIC_SHAPE uuid="4cb91715-7c1b-4fee-a341-417a1451a94d" name="" selectable="True" position="24.305242538,56.321281433,5.939642906" size="3.299999952,2.000000000,2.000000000" orientation="0.329417348,-0.852828205,0.387021214,-0.119928367" local_position="0.000000000,0.000000000,0.000000000" local_size="3.299999952,2.000000000,2.000000000" local_orientation="1.000000000,0.000000000,0.000000000,0.000000000" scaling="1To1" final_shape="False" cast_shadows="True" shape="box" actor="6c39c50b-11e7-4c91-8f51-64d65ff9caaa"/>
  <JOINT uuid="72392b94-938f-4068-8852-5f10dd582921" name="" selectable="True" shapes="['2563ca30-304a-4192-99f7-ba75a77a6e36']" body1="85137694-87ef-4bd3-a279-0e83e8f7694f" body2="6c39c50b-11e7-4c91-8f51-64d65ff9caaa" anchor1="-1.508145690,0.000000000,-0.956643164" anchor2="-6.599999905,1.000000000,-0.600000024" anchor1orientation="0.733980834,-0.031912781,0.500100255,-0.458424956" anchor2orientation="1.000000000,0.000000000,0.000000000,0.000000000" ylimit="9.99998874818e-08" zlimit="9.99998874818e-08" motor_target="1.000000000,0.000000000,0.000000000,0.000000000" motor_on="True"/>
  <DYNAMIC_ACTOR uuid="50913d2d-d5ca-4ba8-8ac9-9594e2abdbe8" name="Bone.010" selectable="True" shapes="['a0b7c47e-2352-4a50-8785-27fe0b162ab6']" position="25.428844452,42.425922394,5.885597706" orientation="-0.024738362,-0.725016117,0.688232183,0.008729819" mass="8.10379123688"/>
  <PHYSIC_SHAPE uuid="a0b7c47e-2352-4a50-8785-27fe0b162ab6" name="" selectable="True" position="25.428752899,42.425888062,5.885784149" size="11.813993454,2.928200245,2.928200245" orientation="-0.024749113,-0.725016713,0.688230932,0.008745229" local_position="0.000000000,0.000000000,0.000000000" local_size="11.813993454,2.928200245,2.928200245" local_orientation="1.000000000,0.000000000,0.000000000,0.000000000" scaling="1To1" final_shape="False" cast_shadows="True" shape="box" actor="50913d2d-d5ca-4ba8-8ac9-9594e2abdbe8"/>
  <JOINT uuid="ac56dae7-4ed8-4a9a-b712-9ed94d34606a" name="" selectable="True" shapes="['ba59f0e6-fa6f-4c5a-b1ae-9cf023d6623c']" body1="6c39c50b-11e7-4c91-8f51-64d65ff9caaa" body2="50913d2d-d5ca-4ba8-8ac9-9594e2abdbe8" anchor1="1.912220478,1.000000715,-0.600001454" anchor2="-11.814000130,0.000001080,0.000002551" anchor1orientation="0.866215587,-0.294563860,0.054570079,0.399905980" anchor2orientation="1.000000000,0.000000000,0.000000000,0.000000000" ylimit="69.9999313354" zlimit="69.9999313354" motor_target="0.984807849,0.000000000,0.173648223,0.000000000" motor_on="True"/>
  <DYNAMIC_ACTOR uuid="3756b3c0-9385-498e-991f-0af0f29a8135" name="Bone.012" selectable="True" shapes="['0d337f43-0295-432c-aa6c-64ef99dbe795']" position="26.091047287,16.981264114,6.605710983" orientation="-0.025079885,-0.707741737,0.706025422,0.000843028" mass="4.37047290802"/>
  <PHYSIC_SHAPE uuid="0d337f43-0295-432c-aa6c-64ef99dbe795" name="" selectable="True" position="26.091012955,16.981227875,6.605759621" size="13.657728195,2.000000000,2.000000000" orientation="-0.025091402,-0.707741976,0.706024766,0.000856965" local_position="0.000000000,0.000000000,0.000000000" local_size="13.657728195,2.000000000,2.000000000" local_orientation="1.000000000,0.000000000,0.000000000,0.000000000" scaling="1To1" final_shape="False" cast_shadows="True" shape="box" actor="3756b3c0-9385-498e-991f-0af0f29a8135"/>
  <JOINT uuid="e4cf45e0-2e94-43e8-9ced-f76278bedaa4" name="" selectable="True" shapes="['05065de6-534a-4ddc-9f30-fd97b05a9094']" body1="50913d2d-d5ca-4ba8-8ac9-9594e2abdbe8" body2="3756b3c0-9385-498e-991f-0af0f29a8135" anchor1="11.814002037,-0.000000133,0.000001419" anchor2="-13.657729149,0.000000025,-0.000000059" anchor1orientation="0.815570593,-0.010303626,0.577985466,0.025922805" anchor2orientation="1.000000000,0.000000000,0.000000000,0.000000000" ylimit="79.9999008179" zlimit="9.9999961853" motor_target="0.819152176,0.000000000,-0.573576570,0.000000000" motor_on="True"/>
  <DYNAMIC_ACTOR uuid="4bbafcc4-9275-46e1-8988-7b52b8131016" name="Bone.014" selectable="True" shapes="['376f07d0-5a64-4358-b6b6-45501e33062c']" position="26.823045731,2.886637449,3.231673479" orientation="0.485380411,-0.587219238,0.474980831,0.440423340" mass="1.56815993786"/>
  <PHYSIC_SHAPE uuid="376f07d0-5a64-4358-b6b6-45501e33062c" name="" selectable="True" position="26.823041916,2.886636496,3.231673002" size="4.900499821,2.000000000,2.000000000" orientation="0.485380471,-0.587219417,0.474980533,0.440423310" local_position="0.000000000,0.000000000,0.000000000" local_size="4.900499821,2.000000000,2.000000000" local_orientation="1.000000000,0.000000000,0.000000000,0.000000000" scaling="1To1" final_shape="False" cast_shadows="True" shape="box" actor="4bbafcc4-9275-46e1-8988-7b52b8131016"/>
  <JOINT uuid="b445858c-b715-4fe5-8ae5-0db40d147149" name="" selectable="True" shapes="['35504bd3-ef05-4c80-bee7-595223ae7b97']" body1="3756b3c0-9385-498e-991f-0af0f29a8135" body2="4bbafcc4-9275-46e1-8988-7b52b8131016" anchor1="13.657729149,0.000000017,-0.000000411" anchor2="-3.920400381,-0.000000373,0.000002913" anchor1orientation="0.729184985,0.095308080,-0.661534905,-0.146891952" anchor2orientation="1.000000000,0.000000000,0.000000000,0.000000000" ylimit="79.9999008179" zlimit="29.9999961853" motor_target="1.000000000,0.000000000,0.000000000,0.000000000" motor_on="True"/>
  <DYNAMIC_ACTOR uuid="1ba82ecf-ef2b-4e6f-bef7-63723ceadfda" name="Bone.002" selectable="True" shapes="['93568388-4536-41c5-8c1d-90718ec34405']" position="19.392999649,66.978393555,4.351601124" orientation="0.723072171,-0.061649833,0.041321434,0.686774015" mass="7.00301122665"/>
  <PHYSIC_SHAPE uuid="93568388-4536-41c5-8c1d-90718ec34405" name="" selectable="True" position="19.393009186,66.978370667,4.352300167" size="3.483786821,6.671902657,3.766114950" orientation="0.723071218,-0.061663728,0.041331749,0.686773121" local_position="0.000000000,0.000000000,0.000000000" local_size="3.483786821,6.671902657,3.766114950" local_orientation="1.000000000,0.000000000,0.000000000,0.000000000" scaling="1To1" final_shape="False" cast_shadows="True" shape="box" actor="1ba82ecf-ef2b-4e6f-bef7-63723ceadfda"/>
  <JOINT uuid="f32b6693-45e2-484b-b8bd-7092d08166e7" name="" selectable="True" shapes="['adfd950e-6be2-48e4-ac06-5d179ab46a1f']" body1="85137694-87ef-4bd3-a279-0e83e8f7694f" body2="1ba82ecf-ef2b-4e6f-bef7-63723ceadfda" anchor1="-1.508145690,0.000000000,-0.956643164" anchor2="-6.735323906,-0.000000005,0.753223717" anchor1orientation="0.781382322,-0.000000084,-0.624052584,0.000000000" anchor2orientation="1.000000000,0.000000000,0.000000000,0.000000000" ylimit="24.9999961853" zlimit="24.9999961853" motor_target="0.999048471,0.000000006,-0.043619405,-0.000000000" motor_on="True"/>
  <DYNAMIC_ACTOR uuid="581543ec-bd97-47fa-acef-10781f65c4cc" name="Bone.003" selectable="True" shapes="['2a5b587d-8cfe-4bdd-a952-ab82a2f4671b']" position="19.930856705,78.555137634,5.709098339" orientation="0.719956934,0.047149617,-0.095268413,0.685830176" mass="24.6568279266"/>
  <PHYSIC_SHAPE uuid="2a5b587d-8cfe-4bdd-a952-ab82a2f4671b" name="" selectable="True" position="19.930858612,78.555122375,5.709381580" size="8.062265396,7.369419098,5.187485695" orientation="0.719957292,0.047145873,-0.095259786,0.685831130" local_position="0.000000000,0.000000000,0.000000000" local_size="8.062265396,7.369419098,5.187485695" local_orientation="1.000000000,0.000000000,0.000000000,0.000000000" scaling="1To1" final_shape="False" cast_shadows="True" shape="box" actor="581543ec-bd97-47fa-acef-10781f65c4cc"/>
  <JOINT uuid="1f3f3aee-f3ef-4ff6-bd4a-ead2f49bfb1f" name="" selectable="True" shapes="['645215a8-18c6-40c6-a562-a6086de8e24d']" body1="1ba82ecf-ef2b-4e6f-bef7-63723ceadfda" body2="581543ec-bd97-47fa-acef-10781f65c4cc" anchor1="3.518500328,-0.000000003,0.753224432" anchor2="-8.062273026,-0.000000106,0.518750966" anchor1orientation="0.984841406,-0.015249334,-0.172764882,-0.002675056" anchor2orientation="1.000000000,0.000000000,0.000000000,0.000000000" ylimit="24.9999961853" zlimit="24.9999961853" motor_target="1.000000000,0.000000000,0.000000000,0.000000000" motor_on="True"/>
  <DYNAMIC_ACTOR uuid="6a95afc0-7381-48e0-a19b-b6964ea96f78" name="Bone.005" selectable="True" shapes="['91f3ad82-e73d-4929-a886-d8575c462e09']" position="13.385391235,83.396240234,7.426573753" orientation="0.002548930,-0.029705765,0.694071829,0.719288111" mass="3.50469851494"/>
  <PHYSIC_SHAPE uuid="91f3ad82-e73d-4929-a886-d8575c462e09" name="" selectable="True" position="13.385413170,83.396255493,7.426693916" size="2.630768061,3.112491608,5.350198746" orientation="0.002554339,-0.029709971,0.694078088,0.719281912" local_position="0.000000000,0.000000000,0.000000000" local_size="2.630768061,3.112491608,5.350198746" local_orientation="1.000000000,0.000000000,0.000000000,0.000000000" scaling="1To1" final_shape="False" cast_shadows="True" shape="box" actor="6a95afc0-7381-48e0-a19b-b6964ea96f78"/>
  <JOINT uuid="0e5cdf56-b39a-4212-a167-fa0262ad36c3" name="" selectable="True" shapes="['5811b4fa-67eb-4b8e-9402-bf0d73d3ea12']" body1="581543ec-bd97-47fa-acef-10781f65c4cc" body2="6a95afc0-7381-48e0-a19b-b6964ea96f78" anchor1="8.062257767,-0.000000063,0.518749654" anchor2="-6.927690983,-0.000000046,2.675092459" anchor1orientation="0.448643565,0.546551764,0.532399654,0.465350032" anchor2orientation="1.000000000,0.000000000,0.000000000,0.000000000" ylimit="4.99999809265" zlimit="4.99999809265" motor_target="0.999048233,0.000000000,0.043619387,0.000000000" motor_on="True"/>
  <DYNAMIC_ACTOR uuid="27479107-52c2-436c-b419-027ced11f066" name="Bone.015" selectable="True" shapes="['c8891dfd-9ee6-4ff2-8de9-838de6344bff']" position="8.309829712,76.116363525,5.979504108" orientation="-0.410424352,-0.501842082,0.516547680,0.559361219" mass="5.61230611801"/>
  <PHYSIC_SHAPE uuid="c8891dfd-9ee6-4ff2-8de9-838de6344bff" name="" selectable="True" position="8.310000420,76.116378784,5.978458405" size="9.899999619,2.420000076,2.928200245" orientation="-0.410377502,-0.501879513,0.516536415,0.559372365" local_position="0.000000000,0.000000000,0.000000000" local_size="9.899999619,2.420000076,2.928200245" local_orientation="1.000000000,0.000000000,0.000000000,0.000000000" scaling="1To1" final_shape="False" cast_shadows="True" shape="box" actor="27479107-52c2-436c-b419-027ced11f066"/>
  <JOINT uuid="7bde4a48-6c9d-4f09-b665-3b4538343ba1" name="" selectable="True" shapes="['596ae36b-fc8c-4d76-a9ca-03830ac93b87']" body1="6a95afc0-7381-48e0-a19b-b6964ea96f78" body2="27479107-52c2-436c-b419-027ced11f066" anchor1="3.072309017,-0.000000009,2.675095797" anchor2="-9.900000572,0.000000244,-0.000005301" anchor1orientation="0.965389371,-0.032193627,0.258675367,-0.008626260" anchor2orientation="1.000000000,0.000000000,0.000000000,0.000000000" ylimit="59.9999313354" zlimit="44.9999694824" motor_target="0.906307876,0.000000000,0.422618359,0.000000000" motor_on="True"/>
  <DYNAMIC_ACTOR uuid="cbcd9334-ddee-4229-b4a9-9be7b4465703" name="Bone.016" selectable="True" shapes="['992be6f0-83b8-4180-b95c-c7e45a950248']" position="5.784617424,59.579124451,2.692188978" orientation="-0.361421764,-0.544101417,0.491902620,0.575638652" mass="2.73791790009"/>
  <PHYSIC_SHAPE uuid="992be6f0-83b8-4180-b95c-c7e45a950248" name="" selectable="True" position="5.784757137,59.579566956,2.689227819" size="7.071068764,2.420000076,2.000000000" orientation="-0.361375421,-0.544135571,0.491889536,0.575646520" local_position="0.000000000,0.000000000,0.000000000" local_size="7.071068764,2.420000076,2.000000000" local_orientation="1.000000000,0.000000000,0.000000000,0.000000000" scaling="1To1" final_shape="False" cast_shadows="True" shape="box" actor="cbcd9334-ddee-4229-b4a9-9be7b4465703"/>
  <JOINT uuid="b7283831-7a09-42fe-b3e1-795a1545ef0d" name="" selectable="True" shapes="['eb26f240-db12-431e-9f36-2d82c9f1fdf0']" body1="27479107-52c2-436c-b419-027ced11f066" body2="cbcd9334-ddee-4229-b4a9-9be7b4465703" anchor1="10.100001335,0.000000079,0.000001911" anchor2="-7.071071148,-0.000000518,-0.000002354" anchor1orientation="0.873894155,0.017611180,0.008695146,-0.485719651" anchor2orientation="1.000000000,0.000000000,0.000000000,0.000000000" ylimit="9.99998874818e-08" zlimit="54.9999809265" motor_target="0.906307936,0.000000000,0.000000000,0.422618359" motor_on="True"/>
  <DYNAMIC_ACTOR uuid="4e0d196c-9f0c-4e3d-bd72-72268cb82cb1" name="Bone.017" selectable="True" shapes="['edcf2860-d14a-4434-99b8-b005045faab6']" position="4.996545315,47.851474762,-0.283211023" orientation="-0.379375190,-0.526310861,0.553006530,0.522738099" mass="1.85599982738"/>
  <PHYSIC_SHAPE uuid="edcf2860-d14a-4434-99b8-b005045faab6" name="" selectable="True" position="4.996732712,47.852245331,-0.287508100" size="4.999999523,2.900000095,1.600000024" orientation="-0.379333645,-0.526339769,0.552993894,0.522752523" local_position="0.000000000,0.000000000,0.000000000" local_size="4.999999523,2.900000095,1.600000024" local_orientation="1.000000000,0.000000000,0.000000000,0.000000000" scaling="1To1" final_shape="False" cast_shadows="True" shape="box" actor="4e0d196c-9f0c-4e3d-bd72-72268cb82cb1"/>
  <JOINT uuid="c58fed00-97da-4444-afb1-133c0bf2c467" name="" selectable="True" shapes="['efc1cc71-2cf9-4b08-ad6a-c97005f102fe']" body1="cbcd9334-ddee-4229-b4a9-9be7b4465703" body2="4e0d196c-9f0c-4e3d-bd72-72268cb82cb1" anchor1="7.071071148,0.000000102,0.000002358" anchor2="-5.000000000,0.580000043,0.960000038" anchor1orientation="0.996465445,0.045070779,0.004159683,0.070766799" anchor2orientation="1.000000000,0.000000000,0.000000000,0.000000000" ylimit="19.9999923706" zlimit="19.9999923706" motor_target="1.000000000,0.000000000,0.000000000,0.000000000" motor_on="True"/>
  <DYNAMIC_ACTOR uuid="dcc489e0-8a8d-4c7e-98ab-2d6efc842411" name="Bone.006" selectable="True" shapes="['386bf395-51f8-4fd6-b890-a3f479c66f68']" position="26.940010071,81.934059143,8.166045189" orientation="0.694875360,-0.715966821,0.035934158,-0.056995928" mass="3.46965122223"/>
  <PHYSIC_SHAPE uuid="386bf395-51f8-4fd6-b890-a3f479c66f68" name="" selectable="True" position="26.940019608,81.934066772,8.166350365" size="2.657341480,3.288831472,4.962572575" orientation="0.694868743,-0.715973020,0.035930898,-0.057000551" local_position="0.000000000,0.000000000,0.000000000" local_size="2.657341480,3.288831472,4.962572575" local_orientation="1.000000000,0.000000000,0.000000000,0.000000000" scaling="1To1" final_shape="False" cast_shadows="True" shape="box" actor="dcc489e0-8a8d-4c7e-98ab-2d6efc842411"/>
  <JOINT uuid="e1670d2e-b569-4bfa-b545-b235a6aed7e2" name="" selectable="True" shapes="['cc5eeb75-4860-438c-8f27-50b5a24f4c0e']" body1="581543ec-bd97-47fa-acef-10781f65c4cc" body2="dcc489e0-8a8d-4c7e-98ab-2d6efc842411" anchor1="8.062257767,-0.000000063,0.518749654" anchor2="-7.263401985,-0.000000217,3.473808527" anchor1orientation="0.446798950,-0.548060954,0.561630905,-0.429616809" anchor2orientation="1.000000000,0.000000000,0.000000000,0.000000000" ylimit="4.99999809265" zlimit="4.99999809265" motor_target="0.999048233,0.000000000,0.043619394,0.000000000" motor_on="True"/>
  <DYNAMIC_ACTOR uuid="f8218c15-5e68-4ff3-8030-80dfe9ffd9e6" name="Bone.018" selectable="True" shapes="['40f4f687-8c48-4116-b84b-861b95bd276e']" position="31.513729095,75.088607788,7.766896725" orientation="0.562037528,-0.502874434,0.468874007,-0.459769905" mass="5.61230516434"/>
  <PHYSIC_SHAPE uuid="40f4f687-8c48-4116-b84b-861b95bd276e" name="" selectable="True" position="31.513742447,75.088600159,7.767241955" size="9.999999046,2.662000179,2.635380268" orientation="0.562036514,-0.502877057,0.468868822,-0.459773511" local_position="0.000000000,0.000000000,0.000000000" local_size="9.999999046,2.662000179,2.635380268" local_orientation="1.000000000,0.000000000,0.000000000,0.000000000" scaling="1To1" final_shape="False" cast_shadows="True" shape="box" actor="f8218c15-5e68-4ff3-8030-80dfe9ffd9e6"/>
  <JOINT uuid="f86a1cd5-5876-4d60-88ca-8cec34281016" name="" selectable="True" shapes="['c4aa8907-9897-4dc4-b28e-0c92d9769a04']" body1="dcc489e0-8a8d-4c7e-98ab-2d6efc842411" body2="f8218c15-5e68-4ff3-8030-80dfe9ffd9e6" anchor1="2.736598015,-0.000000059,3.473805189" anchor2="-10.000000000,0.266200423,0.000004791" anchor1orientation="0.964479148,0.052848466,0.258431435,0.014160707" anchor2orientation="1.000000000,0.000000000,0.000000000,0.000000000" ylimit="59.9999313354" zlimit="44.9999732971" motor_target="0.923879623,0.000000000,0.382683516,0.000000000" motor_on="True"/>
  <DYNAMIC_ACTOR uuid="30489a4e-6bf7-49ce-a515-9befa8ffd505" name="Bone.019" selectable="True" shapes="['faf4cc76-d2d8-447a-a059-c9a08b3073f1']" position="33.930641174,58.930393219,3.741558790" orientation="0.660056055,-0.370725125,0.574530065,-0.311133623" mass="2.73791790009"/>
  <PHYSIC_SHAPE uuid="faf4cc76-d2d8-447a-a059-c9a08b3073f1" name="" selectable="True" position="33.930732727,58.930339813,3.742141724" size="7.071068764,2.420000076,2.000000000" orientation="0.660055876,-0.370728999,0.574525714,-0.311137408" local_position="0.000000000,0.000000000,0.000000000" local_size="7.071068764,2.420000076,2.000000000" local_orientation="1.000000000,0.000000000,0.000000000,0.000000000" scaling="1To1" final_shape="False" cast_shadows="True" shape="box" actor="30489a4e-6bf7-49ce-a515-9befa8ffd505"/>
  <JOINT uuid="31054322-3d34-45b1-a4b8-0e75f79fa94c" name="" selectable="True" shapes="['acefd2f7-3808-4dd8-b64f-66d917ad5e1a']" body1="f8218c15-5e68-4ff3-8030-80dfe9ffd9e6" body2="30489a4e-6bf7-49ce-a515-9befa8ffd505" anchor1="10.000000000,0.266200423,0.000028096" anchor2="-7.071067333,0.725999713,0.000001748" anchor1orientation="0.874056220,0.005021623,-0.001921098,0.485795617" anchor2orientation="1.000000000,0.000000000,0.000000000,0.000000000" ylimit="9.99998874818e-08" zlimit="54.9999160767" motor_target="0.965926051,0.000000000,0.000000000,-0.258819103" motor_on="True"/>
  <DYNAMIC_ACTOR uuid="b18e52de-8a0d-49da-9eb1-d35e20653774" name="Bone.020" selectable="True" shapes="['16f57ff0-fb86-4eb2-8515-8cda68455ce9']" position="34.704048157,48.758735657,-2.704005480" orientation="0.574862123,-0.493702382,0.590005457,-0.278720558" mass="1.85599982738"/>
  <PHYSIC_SHAPE uuid="16f57ff0-fb86-4eb2-8515-8cda68455ce9" name="" selectable="True" position="34.704208374,48.758579254,-2.703230381" size="4.999999523,2.900000095,1.600000024" orientation="0.574861348,-0.493705779,0.590001166,-0.278725117" local_position="0.000000000,0.000000000,0.000000000" local_size="4.999999523,2.900000095,1.600000024" local_orientation="1.000000000,0.000000000,0.000000000,0.000000000" scaling="1To1" final_shape="False" cast_shadows="True" shape="box" actor="b18e52de-8a0d-49da-9eb1-d35e20653774"/>
  <JOINT uuid="415cdcc9-be9a-4710-b0da-c77c2075ee08" name="" selectable="True" shapes="['7733a41b-9afc-4213-9cea-28aa4774abb2']" body1="30489a4e-6bf7-49ce-a515-9befa8ffd505" body2="b18e52de-8a0d-49da-9eb1-d35e20653774" anchor1="7.071071148,0.726000309,-0.000001747" anchor2="-5.000000000,-0.290000021,0.960000038" anchor1orientation="0.988142729,-0.136193544,0.008923348,-0.070325226" anchor2orientation="1.000000000,0.000000000,0.000000000,0.000000000" ylimit="14.9999895096" zlimit="14.9999914169" motor_target="1.000000000,0.000000000,0.000000000,0.000000000" motor_on="True"/>
  <DYNAMIC_ACTOR uuid="82bef5c7-6329-4b0c-9237-5a15eab6597c" name="Bone.007" selectable="True" shapes="['62ef5402-8f46-4295-a042-58c51faf3ef5']" position="20.458816528,92.258323669,7.847236156" orientation="0.722345352,-0.029233679,0.007380072,0.690874934" mass="4.02939081192"/>
  <PHYSIC_SHAPE uuid="62ef5402-8f46-4295-a042-58c51faf3ef5" name="" selectable="True" position="20.458854675,92.258338928,7.847290039" size="6.354526520,2.546584129,3.112491608" orientation="0.722345948,-0.029237065,0.007388116,0.690874040" local_position="0.000000000,0.000000000,0.000000000" local_size="6.354526520,2.546584129,3.112491608" local_orientation="1.000000000,0.000000000,0.000000000,0.000000000" scaling="1To1" final_shape="False" cast_shadows="True" shape="box" actor="82bef5c7-6329-4b0c-9237-5a15eab6597c"/>
  <JOINT uuid="66b5ec7d-32a3-423c-9508-69f8a65f6794" name="" selectable="True" shapes="['3cf11e30-b9cf-4982-84ba-773ad5faf5e2']" body1="581543ec-bd97-47fa-acef-10781f65c4cc" body2="82bef5c7-6329-4b0c-9237-5a15eab6597c" anchor1="8.062257767,-0.000000063,0.518749654" anchor2="-5.930862427,0.000000003,-0.311244607" anchor1orientation="0.985209703,0.015254876,0.170652121,0.002642432" anchor2orientation="1.000000000,0.000000000,0.000000000,0.000000000" ylimit="34.9999961853" zlimit="34.9999961853" motor_target="0.999048233,0.000000000,-0.043619391,0.000000000" motor_on="True"/>
  <DYNAMIC_ACTOR uuid="c86966a3-0e8a-42c6-a205-1c967d0e09ac" name="Bone.008" selectable="True" shapes="['ee5fc51a-099a-40ed-9de8-5e5d6668007d']" position="20.799583435,100.672828674,8.809365273" orientation="0.719047666,0.046500102,-0.071626477,0.689694047" mass="12.6376028061"/>
  <PHYSIC_SHAPE uuid="ee5fc51a-099a-40ed-9de8-5e5d6668007d" name="" selectable="True" position="20.799669266,100.672851563,8.809269905" size="6.655000210,4.244306087,5.592680454" orientation="0.719048858,0.046499737,-0.071617767,0.689693749" local_position="0.000000000,0.000000000,0.000000000" local_size="6.655000210,4.244306087,5.592680454" local_orientation="1.000000000,0.000000000,0.000000000,0.000000000" scaling="1To1" final_shape="False" cast_shadows="True" shape="box" actor="c86966a3-0e8a-42c6-a205-1c967d0e09ac"/>
  <JOINT uuid="f5725947-8267-4013-ac7c-d54b0e5fbc5b" name="" selectable="True" shapes="['83db37d6-4405-498b-8602-149bb901180a']" body1="82bef5c7-6329-4b0c-9237-5a15eab6597c" body2="c86966a3-0e8a-42c6-a205-1c967d0e09ac" anchor1="3.288682938,0.000000000,-0.311243355" anchor2="-5.323999405,0.000000000,-0.559268415" anchor1orientation="0.994028926,-0.000000015,-0.109116882,0.000000000" anchor2orientation="1.000000000,0.000000000,0.000000000,0.000000000" ylimit="39.9999847412" zlimit="39.9999847412" motor_target="1.000000000,0.000000000,0.000000000,0.000000000" motor_on="True"/>
  <STATIC_ACTOR uuid="5c7e210a-f233-4c49-aeee-c1a6145f86ec" name="" selectable="True" shapes="['46ff28ea-b24c-4645-879b-97a454f15463']" position="20.000000000,0.094522946,-2.716273308" orientation="1.000000000,0.000000000,0.000000000,0.000000000"/>
  <PHYSIC_SHAPE uuid="46ff28ea-b24c-4645-879b-97a454f15463" name="" selectable="True" position="20.000000000,0.094522953,-2.716273308" size="14.999999046,1.000000000,14.999999046" orientation="1.000000000,0.000000000,0.000000000,0.000000000" local_position="0.000000000,0.000000007,0.000000000" local_size="14.999999046,1.000000000,14.999999046" local_orientation="1.000000000,0.000000000,0.000000000,0.000000000" scaling="1To1" final_shape="False" cast_shadows="True" shape="box" actor="5c7e210a-f233-4c49-aeee-c1a6145f86ec"/>
  <JOINT uuid="81eafa0b-d1f6-428c-b8d2-6309980739a4" name="" selectable="True" shapes="['09bf667b-e600-48ed-999d-a3e8e4d564e6']" body1="5c7e210a-f233-4c49-aeee-c1a6145f86ec" body2="f99f27d0-68d9-479f-957d-8b88ddfe7656" anchor1="-7.800895214,2.000015259,-0.000012159" anchor2="6.079601288,-0.000000050,-0.000003108" anchor1orientation="0.139544532,-0.677141011,0.698998451,0.182781324" anchor2orientation="1.000000000,0.000000000,0.000000000,0.000000000" ylimit="119.999809265" zlimit="119.999809265" motor_target="0.887010932,0.000000000,-0.461748719,0.000000000" motor_on="True"/>
  <JOINT uuid="b35d1726-b310-4df8-b53e-eb7b6b1dee25" name="" selectable="True" shapes="['e0e824c6-18ba-4b03-b22f-1cff17cca9a0']" body1="5c7e210a-f233-4c49-aeee-c1a6145f86ec" body2="4bbafcc4-9275-46e1-8988-7b52b8131016" anchor1="7.800895214,2.000000000,0.000012398" anchor2="6.079601288,0.000000373,-0.000002913" anchor1orientation="0.182781011,-0.698998451,0.677141070,0.139544800" anchor2orientation="1.000000000,0.000000000,0.000000000,0.000000000" ylimit="119.999809265" zlimit="119.999809265" motor_target="0.887010932,0.000000000,-0.461748719,0.000000000" motor_on="True"/>
  <MESH uuid="86d76d85-8ac6-4f95-bd4d-d6082a1d0450" name="" selectable="False" mesh_file="Character.mesh" bones="[('Bone', '85137694-87ef-4bd3-a279-0e83e8f7694f', 0), ('Bone.001', 'e3be0d2e-cef5-4f63-b73e-d4447353f5e6', '8ebef3b4-24ec-4ff6-840e-5d2e62dc5342'), ('Bone.009', 'dead4a4b-ae6b-4259-93fb-2738cc224787', '3d174f5b-72fb-402a-b319-066b19e025d6'), ('Bone.011', '1c1432fd-9a0e-42d0-a154-cc4dc900ccc0', 'fb5bb77d-018e-4aa2-a444-d6b741e35ee0'), ('Bone.013', 'f99f27d0-68d9-479f-957d-8b88ddfe7656', '8926df68-b341-4c1c-9edc-a84d8c9fb706'), ('Bone.004', '6c39c50b-11e7-4c91-8f51-64d65ff9caaa', '72392b94-938f-4068-8852-5f10dd582921'), ('Bone.010', '50913d2d-d5ca-4ba8-8ac9-9594e2abdbe8', 'ac56dae7-4ed8-4a9a-b712-9ed94d34606a'), ('Bone.012', '3756b3c0-9385-498e-991f-0af0f29a8135', 'e4cf45e0-2e94-43e8-9ced-f76278bedaa4'), ('Bone.014', '4bbafcc4-9275-46e1-8988-7b52b8131016', 'b445858c-b715-4fe5-8ae5-0db40d147149'), ('Bone.002', '1ba82ecf-ef2b-4e6f-bef7-63723ceadfda', 'f32b6693-45e2-484b-b8bd-7092d08166e7'), ('Bone.003', '581543ec-bd97-47fa-acef-10781f65c4cc', '1f3f3aee-f3ef-4ff6-bd4a-ead2f49bfb1f'), ('Bone.005', '6a95afc0-7381-48e0-a19b-b6964ea96f78', '0e5cdf56-b39a-4212-a167-fa0262ad36c3'), ('Bone.015', '27479107-52c2-436c-b419-027ced11f066', '7bde4a48-6c9d-4f09-b665-3b4538343ba1'), ('Bone.016', 'cbcd9334-ddee-4229-b4a9-9be7b4465703', 'b7283831-7a09-42fe-b3e1-795a1545ef0d'), ('Bone.017', '4e0d196c-9f0c-4e3d-bd72-72268cb82cb1', 'c58fed00-97da-4444-afb1-133c0bf2c467'), ('Bone.006', 'dcc489e0-8a8d-4c7e-98ab-2d6efc842411', 'e1670d2e-b569-4bfa-b545-b235a6aed7e2'), ('Bone.018', 'f8218c15-5e68-4ff3-8030-80dfe9ffd9e6', 'f86a1cd5-5876-4d60-88ca-8cec34281016'), ('Bone.019', '30489a4e-6bf7-49ce-a515-9befa8ffd505', '31054322-3d34-45b1-a4b8-0e75f79fa94c'), ('Bone.020', 'b18e52de-8a0d-49da-9eb1-d35e20653774', '415cdcc9-be9a-4710-b0da-c77c2075ee08'), ('Bone.007', '82bef5c7-6329-4b0c-9237-5a15eab6597c', '66b5ec7d-32a3-423c-9508-69f8a65f6794'), ('Bone.008', 'c86966a3-0e8a-42c6-a205-1c967d0e09ac', 'f5725947-8267-4013-ac7c-d54b0e5fbc5b')]" position="16.375850677,1.370891571,-2.020602703" size="1000.000000000,1000.000000000,1000.000000000" orientation="0.999554932,-0.005021887,-0.016082656,-0.024618106" local_pos="-7.133618832,0.000006090,59.999996185" local_quat="0.499999970,0.499999851,-0.499999911,-0.500000119" colour="1.000000000,0.000000000,0.000000000" alpha="0.20000000298" material="Body" final_shape="True"/>
  <CAMERA position="-6.998540401,154.565368652,-167.170181274" orientation="0.058875468,-0.017425582,-0.957326710,-0.282410324"/>
  <OBJECTS name="root-joint" content="list:['engineobject:8ebef3b4-24ec-4ff6-840e-5d2e62dc5342', 'engineobject:72392b94-938f-4068-8852-5f10dd582921']"/>
  <OBJECTS name="foot-joint" content="list:['engineobject:81eafa0b-d1f6-428c-b8d2-6309980739a4', 'engineobject:b35d1726-b310-4df8-b53e-eb7b6b1dee25']"/>
  <OBJECTS name="feet" content="list:['engineobject:4bbafcc4-9275-46e1-8988-7b52b8131016', 'engineobject:f99f27d0-68d9-479f-957d-8b88ddfe7656']"/>
  <OBJECTS name="breast-joint" content="list:['engineobject:1f3f3aee-f3ef-4ff6-bd4a-ead2f49bfb1f']"/>
  <OBJECTS name="uleg" content="list:['engineobject:50913d2d-d5ca-4ba8-8ac9-9594e2abdbe8', 'engineobject:dead4a4b-ae6b-4259-93fb-2738cc224787']"/>
  <OBJECTS name="hip-joint" content="list:['engineobject:ac56dae7-4ed8-4a9a-b712-9ed94d34606a', 'engineobject:3d174f5b-72fb-402a-b319-066b19e025d6']"/>
  <OBJECTS name="hand-joint" content="list:['engineobject:415cdcc9-be9a-4710-b0da-c77c2075ee08', 'engineobject:c58fed00-97da-4444-afb1-133c0bf2c467']"/>
  <OBJECTS name="belly" content="list:['engineobject:1ba82ecf-ef2b-4e6f-bef7-63723ceadfda']"/>
  <OBJECTS name="belly-joint" content="list:['engineobject:f32b6693-45e2-484b-b8bd-7092d08166e7']"/>
  <OBJECTS name="larm" content="list:['engineobject:30489a4e-6bf7-49ce-a515-9befa8ffd505', 'engineobject:cbcd9334-ddee-4229-b4a9-9be7b4465703']"/>
  <OBJECTS name="hip" content="list:['engineobject:e3be0d2e-cef5-4f63-b73e-d4447353f5e6', 'engineobject:6c39c50b-11e7-4c91-8f51-64d65ff9caaa']"/>
  <OBJECTS name="head" content="list:['engineobject:c86966a3-0e8a-42c6-a205-1c967d0e09ac']"/>
  <OBJECTS name="hand" content="list:['engineobject:4e0d196c-9f0c-4e3d-bd72-72268cb82cb1', 'engineobject:b18e52de-8a0d-49da-9eb1-d35e20653774']"/>
  <OBJECTS name="neck-joint" content="list:['engineobject:66b5ec7d-32a3-423c-9508-69f8a65f6794']"/>
  <OBJECTS name="uleg-joint" content="list:['engineobject:e4cf45e0-2e94-43e8-9ced-f76278bedaa4', 'engineobject:fb5bb77d-018e-4aa2-a444-d6b741e35ee0']"/>
  <OBJECTS name="larm-joint" content="list:['engineobject:31054322-3d34-45b1-a4b8-0e75f79fa94c', 'engineobject:b7283831-7a09-42fe-b3e1-795a1545ef0d']"/>
  <OBJECTS name="shoulder-joint" content="list:['engineobject:0e5cdf56-b39a-4212-a167-fa0262ad36c3', 'engineobject:e1670d2e-b569-4bfa-b545-b235a6aed7e2']"/>
  <OBJECTS name="shoulder" content="list:['engineobject:6a95afc0-7381-48e0-a19b-b6964ea96f78', 'engineobject:dcc489e0-8a8d-4c7e-98ab-2d6efc842411']"/>
  <OBJECTS name="neck" content="list:['engineobject:82bef5c7-6329-4b0c-9237-5a15eab6597c']"/>
  <OBJECTS name="uarm-joint" content="list:['engineobject:7bde4a48-6c9d-4f09-b665-3b4538343ba1', 'engineobject:f86a1cd5-5876-4d60-88ca-8cec34281016']"/>
  <OBJECTS name="uarm" content="list:['engineobject:f8218c15-5e68-4ff3-8030-80dfe9ffd9e6', 'engineobject:27479107-52c2-436c-b419-027ced11f066']"/>
  <OBJECTS name="base" content="list:['engineobject:5c7e210a-f233-4c49-aeee-c1a6145f86ec']"/>
  <OBJECTS name="lleg" content="list:['engineobject:3756b3c0-9385-498e-991f-0af0f29a8135', 'engineobject:1c1432fd-9a0e-42d0-a154-cc4dc900ccc0']"/>
  <OBJECTS name="lleg-joint" content="list:['engineobject:8926df68-b341-4c1c-9edc-a84d8c9fb706', 'engineobject:b445858c-b715-4fe5-8ae5-0db40d147149']"/>
  <OBJECTS name="head-joint" content="list:['engineobject:f5725947-8267-4013-ac7c-d54b0e5fbc5b']"/>
  <OBJECTS name="root" content="list:['engineobject:85137694-87ef-4bd3-a279-0e83e8f7694f']"/>
  <OBJECTS name="breast" content="list:['engineobject:581543ec-bd97-47fa-acef-10781f65c4cc']"/>
</scene>
